serapeum_utils/utils.py
serapeum_utils-0.2.0.dist-info/LICENSE.md
serapeum_utils-0.2.0.dist-info/METADATA
serapeum_utils-0.2.0.dist-info/WHEEL
serapeum_utils-0.2.0.dist-info/entry_points.txt
serapeum_utils-0.2.0.dist-info/RECORD
