Metadata-Version: 2.1
Name: serapeum_utils
Version: 0.2.0
Summary: utility package
Home-page: https://github.com/Serapieum-of-alex/serapeum_utils
License: GNU General Public License v3
Keywords: pickle,utils
Author: Mostafa Farrag
Author-email: moah.farag@gmail.com
Requires-Python: >=3.11,<4.0
Classifier: Development Status :: 5 - Production/Stable
Classifier: Environment :: Console
Classifier: Intended Audience :: Developers
Classifier: Intended Audience :: Science/Research
Classifier: License :: OSI Approved :: GNU General Public License v3 (GPLv3)
Classifier: License :: Other/Proprietary License
Classifier: Natural Language :: English
Classifier: Programming Language :: Python :: 3
Classifier: Programming Language :: Python :: 3.11
Classifier: Programming Language :: Python :: 3.12
Classifier: Topic :: Scientific/Engineering :: Visualization
Project-URL: Documentation, https://serapeum_utils.readthedocs.io/
Project-URL: Repository, https://github.com/Serapieum-of-alex/serapeum_utils
